{
	"code":"0000",
	"data":[
		{
			"battery":100,
			"chargeVoltage":379,
			"createTime":1538092446000,
			"direction":353,
			"height":0,
			"iccid":"89860117750007928568",
			"id":1463,
			"isLock":0,
			"latitude":-41.292131,
			"locationMode":12,
			"lockType":2,
			"longitude":174.795668,
			"lstatus":0,
			"mac":"c2898329b5ed",
			"modelNum":"0000000000000000000000000000000000000000",
			"producid":"81003284",
			"psignal":31,
			"pstatus":3932166,
			"speed":0,
			"unlockedTimes":309,
			"updateTime":1542751482000,
			"voltage":416
		},
		{
			"battery":4286,
			"chargeVoltage":0,
			"createTime":1538092446000,
			"direction":345,
			"height":0,
			"iccid":"89860117750007932842",
			"id":1464,
			"isLock":0,
			"latitude":-41.279458,
			"locationMode":11,
			"lockType":2,
			"longitude":174.778891,
			"lstatus":0,
			"mac":"c956873578b0",
			"modelNum":"0000000000000000000000000000000000000000",
			"producid":"81002510",
			"psignal":30,
			"pstatus":3932166,
			"speed":0,
			"unlockedTimes":386,
			"updateTime":1542751474000,
			"voltage":4160
		},
		{
			"battery":97,
			"chargeVoltage":413,
			"createTime":1538092446000,
			"direction":287,
			"height":0,
			"iccid":"89860117750007959449",
			"id":1465,
			"isLock":0,
			"latitude":-41.266544,
			"locationMode":12,
			"lockType":2,
			"longitude":174.781768,
			"lstatus":0,
			"mac":"ff19cee90adc",
			"modelNum":"0000000000000000000000000000000000000000",
			"producid":"81001081",
			"psignal":28,
			"pstatus":3932166,
			"speed":0,
			"unlockedTimes":348,
			"updateTime":1542751372000,
			"voltage":412
		},
		{
			"battery":95,
			"chargeVoltage":74,
			"createTime":1538092449000,
			"direction":213,
			"height":0,
			"iccid":"89860117750007930242",
			"id":1467,
			"isLock":0,
			"latitude":-41.299103,
			"locationMode":12,
			"lockType":2,
			"longitude":174.769383,
			"lstatus":0,
			"mac":"fa917710b09a",
			"modelNum":"0000000000000000000000000000000000000000",
			"producid":"81002478",
			"psignal":23,
			"pstatus":3932166,
			"speed":0,
			"unlockedTimes":353,
			"updateTime":1542751899000,
			"voltage":408
		},
		{
			"battery":98,
			"chargeVoltage":229,
			"createTime":1538094584000,
			"direction":321,
			"height":0,
			"iccid":"89860117750007958144",
			"id":1469,
			"isLock":0,
			"latitude":-41.304221,
			"locationMode":11,
			"lockType":2,
			"longitude":174.79399,
			"lstatus":0,
			"mac":"dc119f5e89fa",
			"modelNum":"0000000000000000000000000000000000000000",
			"producid":"81001129",
			"psignal":27,
			"pstatus":3932166,
			"speed":0,
			"unlockedTimes":406,
			"updateTime":1542751168000,
			"voltage":414
		},
		{
			"battery":100,
			"chargeVoltage":324,
			"createTime":1538700392000,
			"direction":0,
			"height":0,
			"iccid":"89860117750007927297",
			"id":1471,
			"isLock":0,
			"latitude":-41.290691,
			"locationMode":0,
			"lockType":2,
			"longitude":174.773138,
			"lstatus":0,
			"mac":"e206e6130641",
			"modelNum":"0000000000000000000000000000000000000000",
			"producid":"81003078",
			"psignal":29,
			"pstatus":3932166,
			"speed":0,
			"unlockedTimes":303,
			"updateTime":1542751016000,
			"voltage":418
		},
		{
			"battery":4110,
			"chargeVoltage":0,
			"createTime":1538700672000,
			"direction":0,
			"height":0,
			"iccid":"89860117750007926356",
			"id":1477,
			"isLock":0,
			"latitude":-41.251838,
			"locationMode":0,
			"lockType":2,
			"longitude":174.931629,
			"lstatus":0,
			"mac":"d97762105b08",
			"modelNum":"0000000000000000000000000000000000000000",
			"producid":"81003044",
			"psignal":14,
			"pstatus":3932164,
			"speed":0,
			"unlockedTimes":257,
			"updateTime":1542751214000,
			"voltage":4160
		},
		{
			"battery":98,
			"chargeVoltage":421,
			"createTime":1538701160000,
			"direction":336,
			"height":0,
			"iccid":"89860117750007931612",
			"id":1480,
			"isLock":0,
			"latitude":-41.279886,
			"locationMode":13,
			"lockType":2,
			"longitude":174.780098,
			"lstatus":0,
			"mac":"ce2896f3af39",
			"modelNum":"0000000000000000000000000000000000000000",
			"producid":"81002473",
			"psignal":31,
			"pstatus":3932166,
			"speed":0,
			"unlockedTimes":350,
			"updateTime":1542751346000,
			"voltage":414
		},
		{
			"battery":98,
			"chargeVoltage":421,
			"createTime":1538701160000,
			"direction":126,
			"height":0,
			"iccid":"89860117750007931919",
			"id":1481,
			"isLock":0,
			"latitude":-41.279919,
			"locationMode":12,
			"lockType":2,
			"longitude":174.775269,
			"lstatus":0,
			"mac":"ec7b72db0633",
			"modelNum":"0000000000000000000000000000000000000000",
			"producid":"81003513",
			"psignal":27,
			"pstatus":3932166,
			"speed":0,
			"unlockedTimes":395,
			"updateTime":1542752359000,
			"voltage":412
		},
		{
			"battery":98,
			"chargeVoltage":85,
			"createTime":1538701161000,
			"direction":0,
			"height":0,
			"iccid":"89860117750007952162",
			"id":1482,
			"isLock":0,
			"latitude":-41.288071,
			"locationMode":0,
			"lockType":2,
			"longitude":174.779653,
			"lstatus":2,
			"mac":"c0b306998015",
			"modelNum":"0000000000000000000000000000000000000000",
			"producid":"81002144",
			"psignal":27,
			"pstatus":3932167,
			"speed":0,
			"unlockedTimes":358,
			"updateTime":1542752392000,
			"voltage":414
		},
		{
			"battery":100,
			"chargeVoltage":428,
			"createTime":1538701161000,
			"direction":260,
			"height":0,
			"iccid":"89860117750007954333",
			"id":1483,
			"isLock":0,
			"latitude":-41.303106,
			"locationMode":12,
			"lockType":2,
			"longitude":174.777701,
			"lstatus":0,
			"mac":"f634ddf9085a",
			"modelNum":"0000000000000000000000000000000000000000",
			"producid":"81003579",
			"psignal":28,
			"pstatus":3932166,
			"speed":0,
			"unlockedTimes":343,
			"updateTime":1542751392000,
			"voltage":416
		},
		{
			"battery":97,
			"chargeVoltage":408,
			"createTime":1538701305000,
			"direction":11,
			"height":0,
			"iccid":"89860117750007953806",
			"id":1486,
			"isLock":0,
			"latitude":-41.304835,
			"locationMode":12,
			"lockType":2,
			"longitude":174.777571,
			"lstatus":0,
			"mac":"f4975af31b81",
			"modelNum":"0000000000000000000000000000000000000000",
			"producid":"81002164",
			"psignal":29,
			"pstatus":3932166,
			"speed":0,
			"unlockedTimes":433,
			"updateTime":1542751460000,
			"voltage":412
		},
		{
			"battery":85,
			"chargeVoltage":411,
			"createTime":1538701305000,
			"direction":224,
			"height":0,
			"iccid":"89860117750007930168",
			"id":1487,
			"isLock":0,
			"latitude":-41.27946,
			"locationMode":13,
			"lockType":2,
			"longitude":174.778903,
			"lstatus":0,
			"mac":"ff61d47453dc",
			"modelNum":"0000000000000000000000000000000000000000",
			"producid":"81002858",
			"psignal":31,
			"pstatus":3932166,
			"speed":0,
			"unlockedTimes":316,
			"updateTime":1542751289000,
			"voltage":393
		},
		{
			"battery":95,
			"chargeVoltage":338,
			"createTime":1538701306000,
			"direction":111,
			"height":0,
			"iccid":"89860117750007932172",
			"id":1489,
			"isLock":0,
			"latitude":-41.271186,
			"locationMode":13,
			"lockType":2,
			"longitude":174.780441,
			"lstatus":0,
			"mac":"d952364bb54a",
			"modelNum":"0000000000000000000000000000000000000000",
			"producid":"81003596",
			"psignal":26,
			"pstatus":3932166,
			"speed":0,
			"unlockedTimes":303,
			"updateTime":1542751333000,
			"voltage":408
		},
		{
			"battery":41,
			"chargeVoltage":12,
			"createTime":1538701521000,
			"direction":0,
			"height":0,
			"iccid":"89860117750007954994",
			"id":1490,
			"isLock":0,
			"latitude":-41.150825,
			"locationMode":2,
			"lockType":2,
			"longitude":174.837558,
			"lstatus":0,
			"mac":"e104f68f7834",
			"modelNum":"0000000000000000000000000000000000000000",
			"producid":"81002424",
			"psignal":15,
			"pstatus":3932164,
			"speed":0,
			"unlockedTimes":66,
			"updateTime":1542751319000,
			"voltage":360
		},
		{
			"battery":4302,
			"chargeVoltage":0,
			"createTime":1538701521000,
			"direction":114,
			"height":0,
			"iccid":"89860117750007957534",
			"id":1493,
			"isLock":0,
			"latitude":-41.313468,
			"locationMode":12,
			"lockType":2,
			"longitude":174.78125,
			"lstatus":0,
			"mac":"d91dc4910165",
			"modelNum":"0000000000000000000000000000000000000000",
			"producid":"81002588",
			"psignal":30,
			"pstatus":3932166,
			"speed":0,
			"unlockedTimes":451,
			"updateTime":1542751398000,
			"voltage":4160
		},
		{
			"battery":100,
			"chargeVoltage":325,
			"createTime":1538701522000,
			"direction":358,
			"height":0,
			"iccid":"89860117750007924278",
			"id":1494,
			"isLock":0,
			"latitude":-41.304105,
			"locationMode":12,
			"lockType":2,
			"longitude":174.794074,
			"lstatus":0,
			"mac":"e05ebd17de4c",
			"modelNum":"0000000000000000000000000000000000000000",
			"producid":"81003157",
			"psignal":31,
			"pstatus":3932166,
			"speed":0,
			"unlockedTimes":239,
			"updateTime":1542751221000,
			"voltage":419
		},
		{
			"battery":77,
			"chargeVoltage":387,
			"createTime":1538701711000,
			"direction":283,
			"height":0,
			"iccid":"89860117750007932586",
			"id":1495,
			"isLock":0,
			"latitude":-41.282041,
			"locationMode":11,
			"lockType":2,
			"longitude":174.764233,
			"lstatus":0,
			"mac":"c92cf5b3eca1",
			"modelNum":"0000000000000000000000000000000000000000",
			"producid":"81003006",
			"psignal":23,
			"pstatus":3932166,
			"speed":0,
			"unlockedTimes":303,
			"updateTime":1542751471000,
			"voltage":386
		},
		{
			"battery":100,
			"chargeVoltage":434,
			"createTime":1538701714000,
			"direction":234,
			"height":0,
			"iccid":"89860117750007954176",
			"id":1498,
			"isLock":0,
			"latitude":-41.28818,
			"locationMode":12,
			"lockType":2,
			"longitude":174.773888,
			"lstatus":0,
			"mac":"d95f6ad23e61",
			"modelNum":"0000000000000000000000000000000000000000",
			"producid":"81002380",
			"psignal":26,
			"pstatus":3932166,
			"speed":0,
			"unlockedTimes":351,
			"updateTime":1542751403000,
			"voltage":417
		},
		{
			"battery":100,
			"chargeVoltage":421,
			"createTime":1538701923000,
			"direction":300,
			"height":0,
			"iccid":"89860117750007923817",
			"id":1500,
			"isLock":0,
			"latitude":-41.27249,
			"locationMode":13,
			"lockType":2,
			"longitude":174.779286,
			"lstatus":0,
			"mac":"ca22b8604669",
			"modelNum":"0000000000000000000000000000000000000000",
			"producid":"81003429",
			"psignal":31,
			"pstatus":3932166,
			"speed":0,
			"unlockedTimes":221,
			"updateTime":1542751942000,
			"voltage":419
		},
		{
			"battery":94,
			"chargeVoltage":392,
			"createTime":1538702132000,
			"direction":354,
			"height":0,
			"iccid":"89860117750007930812",
			"id":1506,
			"isLock":0,
			"latitude":-41.266423,
			"locationMode":12,
			"lockType":2,
			"longitude":174.781825,
			"lstatus":0,
			"mac":"f6e87907dad2",
			"modelNum":"0000000000000000000000000000000000000000",
			"producid":"81003591",
			"psignal":28,
			"pstatus":3932166,
			"speed":0,
			"unlockedTimes":345,
			"updateTime":1542751239000,
			"voltage":404
		},
		{
			"battery":100,
			"chargeVoltage":434,
			"createTime":1538702132000,
			"direction":68,
			"height":0,
			"iccid":"89860117750007950299",
			"id":1507,
			"isLock":0,
			"latitude":-41.288251,
			"locationMode":12,
			"lockType":2,
			"longitude":174.799983,
			"lstatus":0,
			"mac":"de16909bc843",
			"modelNum":"0000000000000000000000000000000000000000",
			"producid":"81003128",
			"psignal":17,
			"pstatus":3932166,
			"speed":0,
			"unlockedTimes":332,
			"updateTime":1542752389000,
			"voltage":417
		},
		{
			"battery":4302,
			"chargeVoltage":0,
			"createTime":1538702133000,
			"direction":124,
			"height":0,
			"iccid":"89860117750007952071",
			"id":1508,
			"isLock":0,
			"latitude":-41.291296,
			"locationMode":12,
			"lockType":2,
			"longitude":174.779168,
			"lstatus":0,
			"mac":"e5b3e03df1f3",
			"modelNum":"0000000000000000000000000000000000000000",
			"producid":"81003581",
			"psignal":30,
			"pstatus":3932166,
			"speed":0,
			"unlockedTimes":342,
			"updateTime":1542751508000,
			"voltage":4160
		},
		{
			"battery":86,
			"chargeVoltage":7,
			"createTime":1538702302000,
			"direction":359,
			"height":0,
			"iccid":"89860117750007950406",
			"id":1514,
			"isLock":0,
			"latitude":-41.278219,
			"locationMode":12,
			"lockType":2,
			"longitude":174.782101,
			"lstatus":0,
			"mac":"eba82464a3bd",
			"modelNum":"0000000000000000000000000000000000000000",
			"producid":"81001010",
			"psignal":28,
			"pstatus":3932166,
			"speed":0,
			"unlockedTimes":381,
			"updateTime":1542751268000,
			"voltage":394
		},
		{
			"battery":4126,
			"chargeVoltage":0,
			"createTime":1538702680000,
			"direction":0,
			"height":0,
			"iccid":"89860117750007949564",
			"id":1515,
			"isLock":0,
			"latitude":-41.251856,
			"locationMode":1,
			"lockType":2,
			"longitude":174.931231,
			"lstatus":0,
			"mac":"c1a0288fd8de",
			"modelNum":"0000000000000000000000000000000000000000",
			"producid":"81001107",
			"psignal":14,
			"pstatus":3932164,
			"speed":0,
			"unlockedTimes":102,
			"updateTime":1542751319000,
			"voltage":4160
		},
		{
			"battery":92,
			"chargeVoltage":2,
			"createTime":1538702680000,
			"direction":296,
			"height":0,
			"iccid":"89860117750007949580",
			"id":1516,
			"isLock":0,
			"latitude":-41.312135,
			"locationMode":12,
			"lockType":2,
			"longitude":174.781961,
			"lstatus":0,
			"mac":"c049c4d931fd",
			"modelNum":"0000000000000000000000000000000000000000",
			"producid":"81001171",
			"psignal":28,
			"pstatus":3932166,
			"speed":0,
			"unlockedTimes":274,
			"updateTime":1542751399000,
			"voltage":402
		},
		{
			"battery":98,
			"chargeVoltage":426,
			"createTime":1538702680000,
			"direction":17,
			"height":0,
			"iccid":"89860117750007950737",
			"id":1517,
			"isLock":0,
			"latitude":-41.313036,
			"locationMode":12,
			"lockType":2,
			"longitude":174.776976,
			"lstatus":0,
			"mac":"cbbd6e291a84",
			"modelNum":"0000000000000000000000000000000000000000",
			"producid":"81000993",
			"psignal":16,
			"pstatus":3932166,
			"speed":0,
			"unlockedTimes":385,
			"updateTime":1542751397000,
			"voltage":414
		},
		{
			"battery":67,
			"chargeVoltage":379,
			"createTime":1538702680000,
			"direction":283,
			"height":0,
			"iccid":"89860117750007958680",
			"id":1518,
			"isLock":0,
			"latitude":-41.271878,
			"locationMode":12,
			"lockType":2,
			"longitude":174.781948,
			"lstatus":0,
			"mac":"f58c36dbcf49",
			"modelNum":"0000000000000000000000000000000000000000",
			"producid":"81001118",
			"psignal":31,
			"pstatus":3932166,
			"speed":0,
			"unlockedTimes":234,
			"updateTime":1542751714000,
			"voltage":375
		},
		{
			"battery":97,
			"chargeVoltage":404,
			"createTime":1538702835000,
			"direction":177,
			"height":0,
			"iccid":"89860117750007926638",
			"id":1521,
			"isLock":0,
			"latitude":-41.279433,
			"locationMode":11,
			"lockType":2,
			"longitude":174.778925,
			"lstatus":0,
			"mac":"fba11cf6692b",
			"modelNum":"0000000000000000000000000000000000000000",
			"producid":"81003544",
			"psignal":31,
			"pstatus":3932166,
			"speed":0,
			"unlockedTimes":350,
			"updateTime":1542751186000,
			"voltage":412
		},
		{
			"battery":91,
			"chargeVoltage":395,
			"createTime":1538703288000,
			"direction":328,
			"height":0,
			"iccid":"89860117750007926711",
			"id":1525,
			"isLock":0,
			"latitude":-41.313081,
			"locationMode":12,
			"lockType":2,
			"longitude":174.776986,
			"lstatus":0,
			"mac":"f1ba45f2c7bb",
			"modelNum":"0000000000000000000000000000000000000000",
			"producid":"81002637",
			"psignal":20,
			"pstatus":3932166,
			"speed":0,
			"unlockedTimes":288,
			"updateTime":1542751405000,
			"voltage":398
		},
		{
			"battery":100,
			"chargeVoltage":421,
			"createTime":1538703289000,
			"direction":207,
			"height":0,
			"iccid":"89860117750007950117",
			"id":1528,
			"isLock":0,
			"latitude":-41.288489,
			"locationMode":12,
			"lockType":2,
			"longitude":174.776196,
			"lstatus":0,
			"mac":"f0eb3a93c7d9",
			"modelNum":"0000000000000000000000000000000000000000",
			"producid":"81001017",
			"psignal":31,
			"pstatus":3932166,
			"speed":0,
			"unlockedTimes":385,
			"updateTime":1542751487000,
			"voltage":418
		},
		{
			"battery":93,
			"chargeVoltage":395,
			"createTime":1538703608000,
			"direction":355,
			"height":0,
			"iccid":"89860117750007952758",
			"id":1530,
			"isLock":0,
			"latitude":-41.311524,
			"locationMode":12,
			"lockType":2,
			"longitude":174.784051,
			"lstatus":0,
			"mac":"e0ce4b63ef50",
			"modelNum":"0000000000000000000000000000000000000000",
			"producid":"81002215",
			"psignal":22,
			"pstatus":3932166,
			"speed":0,
			"unlockedTimes":219,
			"updateTime":1542751359000,
			"voltage":403
		},
		{
			"battery":91,
			"chargeVoltage":397,
			"createTime":1538703615000,
			"direction":114,
			"height":0,
			"iccid":"89860117750007927321",
			"id":1534,
			"isLock":0,
			"latitude":-41.28674,
			"locationMode":12,
			"lockType":2,
			"longitude":174.758928,
			"lstatus":0,
			"mac":"d9ccce51b4a5",
			"modelNum":"0000000000000000000000000000000000000000",
			"producid":"81003491",
			"psignal":31,
			"pstatus":3932166,
			"speed":0,
			"unlockedTimes":242,
			"updateTime":1542751256000,
			"voltage":399
		},
		{
			"battery":100,
			"chargeVoltage":431,
			"createTime":1538703876000,
			"direction":263,
			"height":0,
			"iccid":"89860117750007953236",
			"id":1536,
			"isLock":0,
			"latitude":-41.27824,
			"locationMode":12,
			"lockType":2,
			"longitude":174.782136,
			"lstatus":0,
			"mac":"f683986ca209",
			"modelNum":"0000000000000000000000000000000000000000",
			"producid":"81002109",
			"psignal":31,
			"pstatus":3932166,
			"speed":0,
			"unlockedTimes":433,
			"updateTime":1542751449000,
			"voltage":417
		},
		{
			"battery":94,
			"chargeVoltage":418,
			"createTime":1538703876000,
			"direction":313,
			"height":0,
			"iccid":"89860117750007957369",
			"id":1537,
			"isLock":0,
			"latitude":-41.279573,
			"locationMode":11,
			"lockType":2,
			"longitude":174.778905,
			"lstatus":0,
			"mac":"dcc95b6cccd7",
			"modelNum":"0000000000000000000000000000000000000000",
			"producid":"81002357",
			"psignal":29,
			"pstatus":3932166,
			"speed":0,
			"unlockedTimes":404,
			"updateTime":1542751482000,
			"voltage":406
		},
		{
			"battery":100,
			"chargeVoltage":288,
			"createTime":1538703876000,
			"direction":153,
			"height":0,
			"iccid":"89860117750007956155",
			"id":1538,
			"isLock":0,
			"latitude":-41.28912,
			"locationMode":12,
			"lockType":2,
			"longitude":174.79917,
			"lstatus":0,
			"mac":"d8fd2abe00e6",
			"modelNum":"0000000000000000000000000000000000000000",
			"producid":"81002120",
			"psignal":17,
			"pstatus":3932166,
			"speed":0,
			"unlockedTimes":244,
			"updateTime":1542751223000,
			"voltage":419
		},
		{
			"battery":98,
			"chargeVoltage":413,
			"createTime":1538704138000,
			"direction":37,
			"height":0,
			"iccid":"89860117750007949671",
			"id":1542,
			"isLock":0,
			"latitude":-41.313441,
			"locationMode":13,
			"lockType":2,
			"longitude":174.791206,
			"lstatus":0,
			"mac":"decde0138cd3",
			"modelNum":"0000000000000000000000000000000000000000",
			"producid":"81000875",
			"psignal":20,
			"pstatus":3932166,
			"speed":0,
			"unlockedTimes":374,
			"updateTime":1542751280000,
			"voltage":414
		},
		{
			"battery":91,
			"chargeVoltage":310,
			"createTime":1538704138000,
			"direction":22,
			"height":0,
			"iccid":"89860117750007931380",
			"id":1543,
			"isLock":0,
			"latitude":-41.314238,
			"locationMode":12,
			"lockType":2,
			"longitude":174.785886,
			"lstatus":0,
			"mac":"de3852dd373f",
			"modelNum":"0000000000000000000000000000000000000000",
			"producid":"81003079",
			"psignal":19,
			"pstatus":3932166,
			"speed":0,
			"unlockedTimes":355,
			"updateTime":1542751434000,
			"voltage":399
		},
		{
			"battery":4302,
			"chargeVoltage":0,
			"createTime":1538704139000,
			"direction":181,
			"height":0,
			"iccid":"89860117750007949846",
			"id":1544,
			"isLock":0,
			"latitude":-41.274901,
			"locationMode":12,
			"lockType":2,
			"longitude":174.784738,
			"lstatus":0,
			"mac":"e19617c10f65",
			"modelNum":"0000000000000000000000000000000000000000",
			"producid":"81000908",
			"psignal":30,
			"pstatus":3932166,
			"speed":0,
			"unlockedTimes":386,
			"updateTime":1542751216000,
			"voltage":4160
		},
		{
			"battery":98,
			"chargeVoltage":413,
			"createTime":1538704352000,
			"direction":0,
			"height":0,
			"iccid":"89860117750007928840",
			"id":1546,
			"isLock":0,
			"latitude":-41.27956,
			"locationMode":12,
			"lockType":2,
			"longitude":174.778983,
			"lstatus":0,
			"mac":"e84148bffce0",
			"modelNum":"0000000000000000000000000000000000000000",
			"producid":"81002631",
			"psignal":31,
			"pstatus":3932166,
			"speed":0,
			"unlockedTimes":189,
			"updateTime":1542751433000,
			"voltage":413
		},
		{
			"battery":100,
			"chargeVoltage":361,
			"createTime":1538704352000,
			"direction":31,
			"height":0,
			"iccid":"89860117750007928147",
			"id":1547,
			"isLock":0,
			"latitude":-41.273168,
			"locationMode":13,
			"lockType":2,
			"longitude":174.779213,
			"lstatus":0,
			"mac":"fad99d0f8219",
			"modelNum":"0000000000000000000000000000000000000000",
			"producid":"81002456",
			"psignal":31,
			"pstatus":3932166,
			"speed":0,
			"unlockedTimes":393,
			"updateTime":1542751284000,
			"voltage":417
		},
		{
			"battery":94,
			"chargeVoltage":395,
			"createTime":1538704352000,
			"direction":316,
			"height":0,
			"iccid":"89860117750007951586",
			"id":1548,
			"isLock":0,
			"latitude":-41.323588,
			"locationMode":12,
			"lockType":2,
			"longitude":174.775081,
			"lstatus":0,
			"mac":"c27e2fdad4f5",
			"modelNum":"0000000000000000000000000000000000000000",
			"producid":"81000988",
			"psignal":31,
			"pstatus":3932166,
			"speed":0,
			"unlockedTimes":384,
			"updateTime":1542751252000,
			"voltage":404
		},
		{
			"battery":71,
			"chargeVoltage":250,
			"createTime":1538704802000,
			"direction":50,
			"height":0,
			"iccid":"89860117750007923767",
			"id":1550,
			"isLock":0,
			"latitude":-41.316473,
			"locationMode":12,
			"lockType":2,
			"longitude":174.778103,
			"lstatus":0,
			"mac":"f0bcdd5ed038",
			"modelNum":"0000000000000000000000000000000000000000",
			"producid":"81003260",
			"psignal":24,
			"pstatus":3932166,
			"speed":0,
			"unlockedTimes":281,
			"updateTime":1542751211000,
			"voltage":380
		},
		{
			"battery":98,
			"chargeVoltage":421,
			"createTime":1538704802000,
			"direction":287,
			"height":0,
			"iccid":"89860117750007932388",
			"id":1551,
			"isLock":0,
			"latitude":-41.266481,
			"locationMode":12,
			"lockType":2,
			"longitude":174.781831,
			"lstatus":0,
			"mac":"fbedf587db2f",
			"modelNum":"0000000000000000000000000000000000000000",
			"producid":"81003232",
			"psignal":22,
			"pstatus":3932166,
			"speed":0,
			"unlockedTimes":242,
			"updateTime":1542751395000,
			"voltage":414
		},
		{
			"battery":100,
			"chargeVoltage":7,
			"createTime":1538704941000,
			"direction":0,
			"height":0,
			"iccid":"89860117750007932685",
			"id":1554,
			"isLock":0,
			"latitude":-41.251893,
			"locationMode":1,
			"lockType":2,
			"longitude":174.931376,
			"lstatus":0,
			"mac":"e7df0d686758",
			"modelNum":"0000000000000000000000000000000000000000",
			"producid":"81002773",
			"psignal":17,
			"pstatus":3932164,
			"speed":0,
			"unlockedTimes":304,
			"updateTime":1542751453000,
			"voltage":417
		},
		{
			"battery":100,
			"chargeVoltage":413,
			"createTime":1538704944000,
			"direction":305,
			"height":0,
			"iccid":"89860117750007924906",
			"id":1558,
			"isLock":0,
			"latitude":-41.27947,
			"locationMode":12,
			"lockType":2,
			"longitude":174.77895,
			"lstatus":0,
			"mac":"df037dcb1bd8",
			"modelNum":"0000000000000000000000000000000000000000",
			"producid":"81003094",
			"psignal":31,
			"pstatus":3932166,
			"speed":0,
			"unlockedTimes":219,
			"updateTime":1542751244000,
			"voltage":417
		},
		{
			"battery":97,
			"chargeVoltage":410,
			"createTime":1538705353000,
			"direction":23,
			"height":0,
			"iccid":"89860117750007929632",
			"id":1559,
			"isLock":0,
			"latitude":-41.29727,
			"locationMode":12,
			"lockType":2,
			"longitude":174.783063,
			"lstatus":0,
			"mac":"fc47e362620b",
			"modelNum":"0000000000000000000000000000000000000000",
			"producid":"81003324",
			"psignal":31,
			"pstatus":3932166,
			"speed":0,
			"unlockedTimes":385,
			"updateTime":1542751374000,
			"voltage":412
		},
		{
			"battery":78,
			"chargeVoltage":348,
			"createTime":1538705353000,
			"direction":322,
			"height":0,
			"iccid":"89860117750007929244",
			"id":1560,
			"isLock":0,
			"latitude":-41.279031,
			"locationMode":12,
			"lockType":2,
			"longitude":174.780781,
			"lstatus":0,
			"mac":"f5d3eadffbcf",
			"modelNum":"0000000000000000000000000000000000000000",
			"producid":"81002834",
			"psignal":23,
			"pstatus":3932166,
			"speed":0,
			"unlockedTimes":297,
			"updateTime":1542751735000,
			"voltage":386
		},
		{
			"battery":98,
			"chargeVoltage":219,
			"createTime":1538705354000,
			"direction":0,
			"height":0,
			"iccid":"89860117750007930549",
			"id":1561,
			"isLock":0,
			"latitude":-41.288976,
			"locationMode":0,
			"lockType":2,
			"longitude":174.774218,
			"lstatus":0,
			"mac":"f80ac8255257",
			"modelNum":"0000000000000000000000000000000000000000",
			"producid":"81003023",
			"psignal":28,
			"pstatus":3932166,
			"speed":0,
			"unlockedTimes":362,
			"updateTime":1542751913000,
			"voltage":413
		},
		{
			"battery":34,
			"chargeVoltage":15,
			"createTime":1538705507000,
			"direction":0,
			"height":0,
			"iccid":"89860117750007932560",
			"id":1562,
			"isLock":0,
			"latitude":-41.275113,
			"locationMode":1,
			"lockType":2,
			"longitude":174.787978,
			"lstatus":0,
			"mac":"dfc0443355e3",
			"modelNum":"0000000000000000000000000000000000000000",
			"producid":"81002847",
			"psignal":25,
			"pstatus":3932164,
			"speed":0,
			"unlockedTimes":75,
			"updateTime":1542751188000,
			"voltage":356
		},
		{
			"battery":100,
			"chargeVoltage":434,
			"createTime":1538705508000,
			"direction":304,
			"height":0,
			"iccid":"89860117750007956544",
			"id":1564,
			"isLock":0,
			"latitude":-41.279546,
			"locationMode":11,
			"lockType":2,
			"longitude":174.778905,
			"lstatus":0,
			"mac":"c6526b32fbc2",
			"modelNum":"0000000000000000000000000000000000000000",
			"producid":"81002165",
			"psignal":29,
			"pstatus":3932166,
			"speed":0,
			"unlockedTimes":329,
			"updateTime":1542751183000,
			"voltage":419
		},
		{
			"battery":98,
			"chargeVoltage":436,
			"createTime":1538705508000,
			"direction":255,
			"height":0,
			"iccid":"89860117750007926430",
			"id":1565,
			"isLock":0,
			"latitude":-41.279426,
			"locationMode":12,
			"lockType":2,
			"longitude":174.778925,
			"lstatus":0,
			"mac":"e1346c0898ae",
			"modelNum":"0000000000000000000000000000000000000000",
			"producid":"81003420",
			"psignal":31,
			"pstatus":3932166,
			"speed":0,
			"unlockedTimes":333,
			"updateTime":1542751242000,
			"voltage":414
		},
		{
			"battery":100,
			"chargeVoltage":423,
			"createTime":1538705663000,
			"direction":349,
			"height":0,
			"iccid":"89860117750007928402",
			"id":1567,
			"isLock":0,
			"latitude":-41.279333,
			"locationMode":12,
			"lockType":2,
			"longitude":174.778885,
			"lstatus":0,
			"mac":"f6e23731b688",
			"modelNum":"0000000000000000000000000000000000000000",
			"producid":"81002776",
			"psignal":31,
			"pstatus":3932166,
			"speed":0,
			"unlockedTimes":422,
			"updateTime":1542751269000,
			"voltage":417
		},
		{
			"battery":100,
			"chargeVoltage":428,
			"createTime":1538705663000,
			"direction":250,
			"height":0,
			"iccid":"89860117750007926448",
			"id":1569,
			"isLock":0,
			"latitude":-41.270071,
			"locationMode":12,
			"lockType":2,
			"longitude":174.78132,
			"lstatus":0,
			"mac":"db9a4a9c7725",
			"modelNum":"0000000000000000000000000000000000000000",
			"producid":"81003223",
			"psignal":26,
			"pstatus":3932166,
			"speed":0,
			"unlockedTimes":339,
			"updateTime":1542751211000,
			"voltage":418
		},
		{
			"battery":100,
			"chargeVoltage":405,
			"createTime":1538705833000,
			"direction":139,
			"height":0,
			"iccid":"89860117750007959373",
			"id":1572,
			"isLock":0,
			"latitude":-41.311806,
			"locationMode":12,
			"lockType":2,
			"longitude":174.779198,
			"lstatus":0,
			"mac":"cc06670b54d0",
			"modelNum":"0000000000000000000000000000000000000000",
			"producid":"81003328",
			"psignal":23,
			"pstatus":3932166,
			"speed":0,
			"unlockedTimes":408,
			"updateTime":1542751442000,
			"voltage":419
		},
		{
			"battery":95,
			"chargeVoltage":132,
			"createTime":1538705833000,
			"direction":0,
			"height":0,
			"iccid":"89860117750007955363",
			"id":1573,
			"isLock":0,
			"latitude":-41.281378,
			"locationMode":1,
			"lockType":2,
			"longitude":174.77818,
			"lstatus":0,
			"mac":"cbbbea52fb8b",
			"modelNum":"0000000000000000000000000000000000000000",
			"producid":"81002647",
			"psignal":27,
			"pstatus":3932164,
			"speed":0,
			"unlockedTimes":318,
			"updateTime":1542751301000,
			"voltage":406
		},
		{
			"battery":83,
			"chargeVoltage":71,
			"createTime":1538705833000,
			"direction":0,
			"height":0,
			"iccid":"89860117750007950166",
			"id":1574,
			"isLock":0,
			"latitude":-41.27588,
			"locationMode":0,
			"lockType":2,
			"longitude":174.771359,
			"lstatus":0,
			"mac":"c462f20663b6",
			"modelNum":"0000000000000000000000000000000000000000",
			"producid":"81001097",
			"psignal":13,
			"pstatus":3932164,
			"speed":0,
			"unlockedTimes":288,
			"updateTime":1542751209000,
			"voltage":391
		},
		{
			"battery":100,
			"chargeVoltage":219,
			"createTime":1538706023000,
			"direction":111,
			"height":0,
			"iccid":"89860117750007925192",
			"id":1575,
			"isLock":0,
			"latitude":-41.299718,
			"locationMode":12,
			"lockType":2,
			"longitude":174.783765,
			"lstatus":0,
			"mac":"c0d123bcdc12",
			"modelNum":"0000000000000000000000000000000000000000",
			"producid":"81003069",
			"psignal":29,
			"pstatus":3932166,
			"speed":0,
			"unlockedTimes":443,
			"updateTime":1542750774000,
			"voltage":415
		},
		{
			"battery":4318,
			"chargeVoltage":0,
			"createTime":1538706294000,
			"direction":306,
			"height":0,
			"iccid":"89860117750007951263",
			"id":1583,
			"isLock":0,
			"latitude":-41.303473,
			"locationMode":13,
			"lockType":2,
			"longitude":174.771801,
			"lstatus":0,
			"mac":"d7c037221762",
			"modelNum":"0000000000000000000000000000000000000000",
			"producid":"81000878",
			"psignal":30,
			"pstatus":3932166,
			"speed":0,
			"unlockedTimes":255,
			"updateTime":1542751314000,
			"voltage":4160
		},
		{
			"battery":100,
			"chargeVoltage":421,
			"createTime":1538706294000,
			"direction":162,
			"height":0,
			"iccid":"89860117750007959126",
			"id":1584,
			"isLock":0,
			"latitude":-41.311151,
			"locationMode":11,
			"lockType":2,
			"longitude":174.781748,
			"lstatus":0,
			"mac":"cc9fd5921eb4",
			"modelNum":"0000000000000000000000000000000000000000",
			"producid":"81001019",
			"psignal":23,
			"pstatus":3932166,
			"speed":0,
			"unlockedTimes":463,
			"updateTime":1542751486000,
			"voltage":417
		},
		{
			"battery":96,
			"chargeVoltage":409,
			"createTime":1538706294000,
			"direction":0,
			"height":0,
			"iccid":"89860117750007959423",
			"id":1585,
			"isLock":0,
			"latitude":-41.286006,
			"locationMode":0,
			"lockType":2,
			"longitude":174.777789,
			"lstatus":0,
			"mac":"cd1645bfefca",
			"modelNum":"0000000000000000000000000000000000000000",
			"producid":"81000939",
			"psignal":31,
			"pstatus":3932166,
			"speed":0,
			"unlockedTimes":354,
			"updateTime":1542750774000,
			"voltage":409
		},
		{
			"battery":98,
			"chargeVoltage":421,
			"createTime":1538706295000,
			"direction":65,
			"height":0,
			"iccid":"89860117750007950810",
			"id":1586,
			"isLock":0,
			"latitude":-41.292266,
			"locationMode":11,
			"lockType":2,
			"longitude":174.778221,
			"lstatus":0,
			"mac":"c50a5b0e2bb2",
			"modelNum":"0000000000000000000000000000000000000000",
			"producid":"81001204",
			"psignal":31,
			"pstatus":3932166,
			"speed":0,
			"unlockedTimes":447,
			"updateTime":1542751126000,
			"voltage":414
		},
		{
			"battery":98,
			"chargeVoltage":413,
			"createTime":1538706493000,
			"direction":197,
			"height":0,
			"iccid":"89860117750007929699",
			"id":1587,
			"isLock":0,
			"latitude":-41.279605,
			"locationMode":11,
			"lockType":2,
			"longitude":174.778994,
			"lstatus":0,
			"mac":"de9933189bd4",
			"modelNum":"0000000000000000000000000000000000000000",
			"producid":"81003563",
			"psignal":31,
			"pstatus":3932166,
			"speed":0,
			"unlockedTimes":333,
			"updateTime":1542751176000,
			"voltage":414
		},
		{
			"battery":98,
			"chargeVoltage":405,
			"createTime":1538706607000,
			"direction":28,
			"height":0,
			"iccid":"89860117750007930358",
			"id":1590,
			"isLock":0,
			"latitude":-41.297485,
			"locationMode":12,
			"lockType":2,
			"longitude":174.78309,
			"lstatus":0,
			"mac":"e4b73c38d1ab",
			"modelNum":"0000000000000000000000000000000000000000",
			"producid":"81002803",
			"psignal":31,
			"pstatus":3932166,
			"speed":0,
			"unlockedTimes":313,
			"updateTime":1542751390000,
			"voltage":413
		},
		{
			"battery":4318,
			"chargeVoltage":0,
			"createTime":1538706607000,
			"direction":102,
			"height":0,
			"iccid":"89860117750007952774",
			"id":1591,
			"isLock":0,
			"latitude":-41.279436,
			"locationMode":13,
			"lockType":2,
			"longitude":174.77891,
			"lstatus":0,
			"mac":"c4c4aa747161",
			"modelNum":"0000000000000000000000000000000000000000",
			"producid":"81002244",
			"psignal":30,
			"pstatus":3932166,
			"speed":0,
			"unlockedTimes":319,
			"updateTime":1542751293000,
			"voltage":4160
		},
		{
			"battery":77,
			"chargeVoltage":361,
			"createTime":1538706607000,
			"direction":317,
			"height":0,
			"iccid":"89860117750007932057",
			"id":1592,
			"isLock":0,
			"latitude":-41.307698,
			"locationMode":12,
			"lockType":2,
			"longitude":174.777571,
			"lstatus":0,
			"mac":"e356145ce856",
			"modelNum":"0000000000000000000000000000000000000000",
			"producid":"81003351",
			"psignal":31,
			"pstatus":3932166,
			"speed":0,
			"unlockedTimes":253,
			"updateTime":1542751406000,
			"voltage":385
		},
		{
			"battery":100,
			"chargeVoltage":426,
			"createTime":1538706607000,
			"direction":166,
			"height":0,
			"iccid":"89860117750007930622",
			"id":1593,
			"isLock":0,
			"latitude":-41.279486,
			"locationMode":13,
			"lockType":2,
			"longitude":174.77897,
			"lstatus":0,
			"mac":"ce91245c36f3",
			"modelNum":"0000000000000000000000000000000000000000",
			"producid":"81002994",
			"psignal":31,
			"pstatus":3932166,
			"speed":0,
			"unlockedTimes":338,
			"updateTime":1542751319000,
			"voltage":415
		},
		{
			"battery":98,
			"chargeVoltage":390,
			"createTime":1538706798000,
			"direction":123,
			"height":0,
			"iccid":"89860117750007924542",
			"id":1596,
			"isLock":0,
			"latitude":-41.318913,
			"locationMode":11,
			"lockType":2,
			"longitude":174.801131,
			"lstatus":0,
			"mac":"ce705fe2c67e",
			"modelNum":"0000000000000000000000000000000000000000",
			"producid":"81003300",
			"psignal":20,
			"pstatus":3932166,
			"speed":0,
			"unlockedTimes":352,
			"updateTime":1542751466000,
			"voltage":413
		},
		{
			"battery":97,
			"chargeVoltage":421,
			"createTime":1538706799000,
			"direction":118,
			"height":0,
			"iccid":"89860117750007955009",
			"id":1597,
			"isLock":0,
			"latitude":-41.304846,
			"locationMode":12,
			"lockType":2,
			"longitude":174.777431,
			"lstatus":0,
			"mac":"c850127f2e16",
			"modelNum":"0000000000000000000000000000000000000000",
			"producid":"81002590",
			"psignal":28,
			"pstatus":3932166,
			"speed":0,
			"unlockedTimes":427,
			"updateTime":1542751261000,
			"voltage":413
		},
		{
			"battery":98,
			"chargeVoltage":423,
			"createTime":1538706966000,
			"direction":149,
			"height":0,
			"iccid":"89860117750007929863",
			"id":1599,
			"isLock":0,
			"latitude":-41.31124,
			"locationMode":13,
			"lockType":2,
			"longitude":174.783996,
			"lstatus":0,
			"mac":"c3211c9bd0c4",
			"modelNum":"0000000000000000000000000000000000000000",
			"producid":"81003577",
			"psignal":27,
			"pstatus":3932166,
			"speed":0,
			"unlockedTimes":316,
			"updateTime":1542751332000,
			"voltage":414
		},
		{
			"battery":98,
			"chargeVoltage":378,
			"createTime":1538706989000,
			"direction":318,
			"height":0,
			"iccid":"89860117750007932651",
			"id":1600,
			"isLock":0,
			"latitude":-41.304028,
			"locationMode":11,
			"lockType":2,
			"longitude":174.800849,
			"lstatus":0,
			"mac":"dee53084c3d3",
			"modelNum":"0000000000000000000000000000000000000000",
			"producid":"81002962",
			"psignal":23,
			"pstatus":3932166,
			"speed":0,
			"unlockedTimes":201,
			"updateTime":1542750932000,
			"voltage":414
		},
		{
			"battery":4302,
			"chargeVoltage":0,
			"createTime":1538706989000,
			"direction":327,
			"height":0,
			"iccid":"89860117750007930739",
			"id":1601,
			"isLock":0,
			"latitude":-41.282445,
			"locationMode":12,
			"lockType":2,
			"longitude":174.779049,
			"lstatus":0,
			"mac":"dda3bdb293af",
			"modelNum":"0000000000000000000000000000000000000000",
			"producid":"81002909",
			"psignal":30,
			"pstatus":3932166,
			"speed":0,
			"unlockedTimes":276,
			"updateTime":1542751407000,
			"voltage":4160
		},
		{
			"battery":100,
			"chargeVoltage":419,
			"createTime":1538712364000,
			"direction":199,
			"height":0,
			"iccid":"89860117750007927743",
			"id":1605,
			"isLock":0,
			"latitude":-41.31598,
			"locationMode":12,
			"lockType":2,
			"longitude":174.778081,
			"lstatus":0,
			"mac":"eb55de366f80",
			"modelNum":"0000000000000000000000000000000000000000",
			"producid":"81002792",
			"psignal":21,
			"pstatus":3932166,
			"speed":0,
			"unlockedTimes":240,
			"updateTime":1542751474000,
			"voltage":415
		},
		{
			"battery":89,
			"chargeVoltage":389,
			"createTime":1538712940000,
			"direction":151,
			"height":0,
			"iccid":"89860117750007933014",
			"id":1608,
			"isLock":0,
			"latitude":-41.27947,
			"locationMode":12,
			"lockType":2,
			"longitude":174.778963,
			"lstatus":0,
			"mac":"cba3a1daee30",
			"modelNum":"0000000000000000000000000000000000000000",
			"producid":"81003329",
			"psignal":31,
			"pstatus":3932166,
			"speed":0,
			"unlockedTimes":369,
			"updateTime":1542751361000,
			"voltage":396
		},
		{
			"battery":95,
			"chargeVoltage":382,
			"createTime":1538715934000,
			"direction":142,
			"height":0,
			"iccid":"89860117750007930630",
			"id":1610,
			"isLock":0,
			"latitude":-41.268919,
			"locationMode":12,
			"lockType":2,
			"longitude":174.778504,
			"lstatus":0,
			"mac":"e48e2bfc9e58",
			"modelNum":"0000000000000000000000000000000000000000",
			"producid":"81003159",
			"psignal":22,
			"pstatus":3932166,
			"speed":0,
			"unlockedTimes":239,
			"updateTime":1542751280000,
			"voltage":408
		},
		{
			"battery":98,
			"chargeVoltage":418,
			"createTime":1538735030000,
			"direction":10,
			"height":0,
			"iccid":"89860117750007929095",
			"id":1612,
			"isLock":0,
			"latitude":-41.248908,
			"locationMode":13,
			"lockType":2,
			"longitude":174.812699,
			"lstatus":0,
			"mac":"edbff3e08ea9",
			"modelNum":"0000000000000000000000000000000000000000",
			"producid":"81002668",
			"psignal":23,
			"pstatus":3932166,
			"speed":0,
			"unlockedTimes":242,
			"updateTime":1542751288000,
			"voltage":413
		},
		{
			"battery":100,
			"chargeVoltage":416,
			"createTime":1538735101000,
			"direction":74,
			"height":0,
			"iccid":"89860117750007950224",
			"id":1613,
			"isLock":0,
			"latitude":-41.320596,
			"locationMode":12,
			"lockType":2,
			"longitude":174.775611,
			"lstatus":0,
			"mac":"c5ef44e22a4c",
			"modelNum":"0000000000000000000000000000000000000000",
			"producid":"81001134",
			"psignal":27,
			"pstatus":3932166,
			"speed":0,
			"unlockedTimes":289,
			"updateTime":1542751309000,
			"voltage":420
		},
		{
			"battery":92,
			"chargeVoltage":0,
			"createTime":1541745011000,
			"direction":0,
			"height":0,
			"iccid":"00000",
			"id":1698,
			"isLock":0,
			"latitude":-41.2116,
			"locationMode":0,
			"lockType":2,
			"longitude":174.83,
			"lstatus":0,
			"mac":"0000",
			"modelNum":"0000000000000000000000000000000000000000",
			"producid":"e4e2b7a7-9cc",
			"psignal":0,
			"pstatus":3932166,
			"speed":0,
			"unlockedTimes":0,
			"updateTime":1542752363000,
			"voltage":39
		}
	],
	"msg":"Successful"
}